vdict/__init__.py
vdict/version.py
vdict-0.1.0.dist-info/LICENSE
vdict-0.1.0.dist-info/METADATA
vdict-0.1.0.dist-info/WHEEL
vdict-0.1.0.dist-info/top_level.txt
vdict-0.1.0.dist-info/RECORD
