Metadata-Version: 2.1
Name: vdict
Version: 0.1.0
Summary: A dict with a vector index for fast lookup of nearest neighbors
Home-page: https://github.com/ur-whitelab/vdict
Author: Andrew White
Author-email: andrew.white@rochester.edu
License: MIT
Classifier: Programming Language :: Python :: 3
Classifier: License :: OSI Approved :: MIT License
Classifier: Operating System :: OS Independent
License-File: LICENSE
Requires-Dist: hnswlib
Requires-Dist: numpy
